{
	"uid": "outside2.wad",
	"name": "Outside For Doom 2",
	"description": "Outside basicly. A huge level with billions (Well, okay, a lot) of buildings, rivers that interconnect, and lots of hidden areas, and far too much VIOLENCE!!!!!!",
	"date": "2015-09-14 21:01:02",
	"files": [
		{
			"filename": "outside2.wad",
			"size": 1418364,
			"crc": 656568007,
			"md5": "10dc2fb0dcd60c925513f4447481d28d",
			"sha1": "1badb1e22a0ea67ed00e0e00bc2de2e28dec4e4a",
			"sha256": "c2afdb7ec5baa38c1857ad05e37ed330dea107125210ee294c87453bce4f849d"
		}
	]
}