{
	"uid": "DISORDER (06673e).wad",
	"name": "Disorder",
	"description": "All (almost) monsters are in this level, ALL ? ... aaaahhhhh !!! It's a disorder level, it's my first level. I hope, you have fun !! I work at more, base level !!!",
	"version": "06673e",
	"date": "2014-11-01 14:52:46",
	"files": [
		{
			"filename": "DISORDER.wad",
			"size": 45289,
			"crc": 3919776584,
			"md5": "eb798543baae96fa21be9201dad9c9a3",
			"sha1": "06673eace95f5a5fc02d0c9c1bd6977f896b9d31",
			"sha256": "5941eafb520730842ebe1c41462e802c85462844477944c325a1378a9885f627"
		}
	]
}