{
	"uid": "macsound.wad",
	"name": "MACVILEWHORE'S SUPER DUPER YAY sound wad",
	"description": "This wad, which is SW33t ch3rri0s, gives almost every single thing in the game its own sound. Almost all sounds replaced or updated, the ones that are NOT new I made louder, or I modyfied them a bit.",
	"date": "2015-09-14 20:37:43",
	"files": [
		{
			"filename": "macsound.wad",
			"size": 10199788,
			"crc": 2963281563,
			"md5": "3a7e4998a95d1204980dd91212e1da72",
			"sha1": "f57a5c2bffe68c6d71d9e0685d8cf5272b91063b",
			"sha256": "ce9d387f538a08eb1eacf6017772032a7637873d2f72c9794a4bfc85d5595e6e"
		}
	]
}