{
	"uid": "slosh.wad",
	"name": "Fucking Hostile Psychoholic Slosh",
	"description": "6 new and very hard (but fair) levels for Doom2 that took me months to plan out and create. These levels are as fine tuned and detailed as the real Doom2 levels but are recomended for above average players only. Sorry, but not created for deathmatch or cooperative. SAVE OFTEN OR DIE!!!",
	"date": "2013-11-06 22:33:11",
	"files": [
		{
			"filename": "slosh.wad",
			"size": 422578,
			"crc": 2313286607,
			"md5": "9e2b5507beae2a9f831928d7558d9d0c",
			"sha1": "77435ed4e50c05298060416b328832ed4fc8895a",
			"sha256": "77e48efc5f8b2bd949a24afe8c565b7ed2e402f036ffc9e0dfd4e45877a0f5e6"
		}
	]
}