{
	"uid": "impy1.wad",
	"name": "impy1.wad",
	"description": "This is the demo of a three part wad where you must take you plasma rifle and blast through thousands of imps. The purpose of making this was to see if i could get this on the infamous list on doomworld. Also, run this wad using JDoom, iremember there being alot of bugs running regulary.",
	"date": "2014-12-24 19:01:42",
	"files": [
		{
			"filename": "impy1.wad",
			"size": 884626,
			"crc": 218910470,
			"md5": "27b59512de825dace7f50f1da3bb8d84",
			"sha1": "24121522c4ffe9bcee4cba3af20f398f85351791",
			"sha256": "0c0a065e23e51f05c5f4076c54b60f6531325c7d27bd493276f8625a337984ef"
		}
	]
}