{
	"uid": "unbeliev.wad",
	"name": "UnBeliever",
	"description": "A whole new dimension of UnAligned! The death of the Icons of Sin shattered reality and thrust you into a strange dimension of swords and sorcery. Now you must survive three distinct, dastardly episodes and defeat the three D'Sparils!",
	"date": "2019-08-04 01:12:32",
	"files": [
		{
			"filename": "unbeliev.wad",
			"size": 2062526,
			"crc": 1687621883,
			"md5": "0996d65d32ce9287edfa59ee65f6b61b",
			"sha1": "33f9bb65f4eb38cc93614c86d4508352a63586b5",
			"sha256": "18bafc8d5258a4277452119712e43b6d6a79481ada52089487a794b45d9cf980"
		}
	]
}