{
	"uid": "anniweap.wad",
	"name": "The Annihilator weapon",
	"description": "Tired of overpowered monsters? Tired of having no proper weapon to wither down that two-hundred thousand odd health monster? Well look no further, Introducing, the Annihilator! It's super-duper overpoweredness is so overpowered, it will bring down a Two-hundred thousand odd health monster in seconds! Because of this overpoweredness; however, the Annihilator is not for everyone! It's side effects may include: Head Ache, Nausea, Seizures, and not actually annihilating your target! So what are you waiting for!? Get yourself one of these big nasty guns today, and start getting rid of your hideously overpowered monsters with a hideously overpowered weapon! (No, I will not parody generic advertisements every time I release a weapon, the parody is for this weapon only.)",
	"date": "2015-09-15 18:10:40",
	"files": [
		{
			"filename": "anniweap.wad",
			"size": 45446,
			"crc": 1136744817,
			"md5": "7a511bd67c87fc98957518091336d265",
			"sha1": "09f5714c0767100d6098266fcbed72155b4515e0",
			"sha256": "85e6e72956161e35a3da57cce47dbc77d29477b83df97526c8e3479481e5aef9"
		}
	]
}