{
	"uid": "ss_e2_m1 (93fc76).wad",
	"name": "StarShip DOOM!!!",
	"description": "During a routine mission to the Federation outpost on Deimos, the Starship California was taken over by a evil race of aliens. To your surprise, they look much like the Hellspawn from your own world's past. As captain of your Starship you must protect the safety of the Federation, and of course your Starship!! So grab that pistol and go get 'em!!!",
	"version": "93fc76",
	"date": "2013-11-02 16:02:45",
	"files": [
		{
			"filename": "ss_e2_m1.wad",
			"size": 216663,
			"crc": 977742414,
			"md5": "b56454bd43b3b535ef824091d0807fc5",
			"sha1": "93fc763e01d4a00a3ca5702e5fc779457d8d4bf0",
			"sha256": "32ee664f2f968343e720f5812f2efe0cf084a5bee64e35250d89d4103a4123b5"
		}
	]
}