{
	"uid": "dm2keved.wad",
	"name": "DM-KevEd.",
	"description": "Quick & Tough DM level for DOOM ][. Fast action wad, many ways to go, but not too much :) With two main areas, the DethPit (tm) and the Terroridor (tm) all with a great speed, fast pace music.",
	"date": "2014-01-07 22:27:18",
	"files": [
		{
			"filename": "dm2keved.wad",
			"size": 481969,
			"crc": 11690210,
			"md5": "228168a3604ed940f4b261da7ec72e80",
			"sha1": "6381c64f59ecf83431030330b897b0368622daa3",
			"sha256": "c6568a8f05c5adcf1aa712926b176c45954dded4c8675710f54b1cf0f2e98797"
		}
	]
}