{
	"uid": "termi950.wad",
	"name": "\"T-950 strikes\"",
	"description": "My second decorate weapon mod. But don't ask me how the Terminator T-950 appeared on the UAC base and why IT started killing demons. Let's say, IT just did... and used all its arsenal for this little one-hell-of-a-party.",
	"date": "2018-03-27 21:12:55",
	"files": [
		{
			"filename": "termi950.wad",
			"size": 2335267,
			"crc": 349715604,
			"md5": "0ee190c0a347a7edffa70026082ce001",
			"sha1": "51c0e63918f535042bd6208b158247725903a95a",
			"sha256": "5c8bf7ab46d7b486f13c117ac98c760496eac83a2d4a5db447e0989f107bec3c"
		}
	]
}