{
	"uid": "mud.wad",
	"name": "Mud (dont ask me why.  I just felt like calling it",
	"description": "You've been assigned to infultrate an area inhabited by cyberdemons and spiderdemons to destroy kill, maim and do various other fun things to every living thing you see. Many others have tryed and failed and thier worthless bodies litter the wall and floor. To tell the truth this is impossible. But dont let that dishearten you. Get out there and be a man (that means dont cheat). Have FUN! heh heh heh...",
	"date": "2015-09-14 23:28:59",
	"files": [
		{
			"filename": "mud.wad",
			"size": 80740,
			"crc": 2803960222,
			"md5": "e1a0597ecf09c1edc29d04b6060b9033",
			"sha1": "382892736a48ed24eed8b13d7f35018b26c721cc",
			"sha256": "a3dc751de2b4afc57686414e580aacdbecef945f077e54f1bab93760d51d015f"
		}
	]
}