{
	"uid": "newordr (ee6fa3).wad",
	"name": "The New Order",
	"description": "It's clear to me that there are very few strife wads on /idgames, so I decided why not make a whole megawad of strife maps? Enjoy 20 levels of fun strife action!",
	"version": "ee6fa3",
	"date": "2014-12-14 20:58:26",
	"files": [
		{
			"filename": "newordr.wad",
			"size": 13878631,
			"crc": 390871922,
			"md5": "013d75a604b4df2cc421b48b44708696",
			"sha1": "ee6fa3352b0e28b1768d4c45c15e1cad4a90658b",
			"sha256": "31b7f6c707f3e127cfb9b17a7f3c1bb1cc5e0221e00428d0edde377eef5b73cb"
		}
	]
}