{
	"uid": "kether.wad",
	"name": "Kether",
	"description": "While on your daily stroll around of the disgusting brown hillside, you hear a scream. Eager to loot the corpse of whoever probably just died, you grab you pistol and head in the direction of the scream. What you find instead will make you question everything you've ever known... Really, It's just a map I made so I looked as if I was doing something productive. Enjoy!",
	"date": "2015-09-15 16:45:17",
	"files": [
		{
			"filename": "kether.wad",
			"size": 339990,
			"crc": 2968041721,
			"md5": "1f3fa49c63bb12ee35847fde5badaa9f",
			"sha1": "0fe4f7d0e24ef8da1c11e2a345eb7d0bdfa9d115",
			"sha256": "434d04a0da731f8da33220dcfb66a02817fbfb6487d2a44eadbfedee8c51329c"
		}
	]
}