{
	"uid": "talons5.wad",
	"name": "Talons of the Beast (Part 5)",
	"description": "Playable singleplayer, co-op or deathmatch. You have defeated the demon champion, and ransacked their base. As the flash of another teleport surrounds you, you wonder what you will face next.",
	"date": "2014-01-07 21:49:04",
	"files": [
		{
			"filename": "talons5.wad",
			"size": 82314,
			"crc": 1724678772,
			"md5": "c4f31fcd3e211aca9315252caf66f8bd",
			"sha1": "0eb2d45eddebd63902f22070b7ef360d0e0af74d",
			"sha256": "7493a1dc8ee45da3af18aab692db2654a31b47dfb998ce2452893238869aea89"
		}
	]
}