{
	"uid": "rabid (0bdd81).wad",
	"name": "RABID.WAD",
	"description": "Close quarter melee with that favorite of weapons, the Shot Gun. Compact, detailed level in the spirit of ID's original first episode. If you're fed up of panoramic blast-o-thon's and \"Oh my, there's a Cyberdemon next to the player one start.\" then this is for you.",
	"version": "0bdd81",
	"date": "2014-01-11 11:17:07",
	"files": [
		{
			"filename": "rabid.wad",
			"size": 94061,
			"crc": 61012126,
			"md5": "a2e149414b19d9f379935feb31064e70",
			"sha1": "0bdd8172eb80b629a7743fead9bbba88221433d7",
			"sha256": "f451318b348af7fe80b409dd92f1f974bdaa8decf5a6a30f1358b722b7274790"
		}
	]
}