{
	"uid": "bop.wad",
	"name": "bop.wad  -Baron on a Pedastal",
	"description": "Dark and Forboding, a trip into the dark side of Diemos. Has numerous teleporters, and a few stair cases, just to keep up with my first wad. Their not huge, but very interesting. Didn't implement and secret doors or sectors. There are many Barons of Hell, and one guarding the blue key on a platform (hence the title)",
	"date": "2013-11-02 15:23:04",
	"files": [
		{
			"filename": "bop.wad",
			"size": 110838,
			"crc": 1021528901,
			"md5": "ce01a8afb930ecebfaf516d29bca719e",
			"sha1": "a0604c02d746af9bfbdaeed6734d7c1a5a969326",
			"sha256": "90b27fadd7b549c5fabed7af786203c57e5ca4895bdef1ad9eb21930cfcfd77f"
		}
	]
}