{
	"uid": "idmqwcon.wad",
	"name": "Idoom mapping contest #1: Quake World",
	"description": "Quake themed wad comprising 7 maps and each was made by different author. The point of this project was to bring more beginers into mapping and give him feed-back. MAP LIST ------------------------ MAP01 - Easy Start Author: Klofkac",
	"date": "2014-12-22 18:58:37",
	"files": [
		{
			"filename": "idmqwcon.wad",
			"size": 19168326,
			"crc": 1734731051,
			"md5": "91f9a2919627de0df8735efe2107dcce",
			"sha1": "862525b6c47f44c7d5c4a0b03af3dcc205c02282",
			"sha256": "a8397f569fd503f7c4f5c0c6cfbaba59a72f9075f866b19b2e00f8b94279af9c"
		}
	]
}