{
	"uid": "csre2m1 (53c8aa).wad",
	"name": "CSRE1M1.WAD",
	"description": "You have just returned from Hell and find yourself somewhere worse. That's right in Oblivion, you must have iritated someone in Hell, so strap on your pistol and follow where other marines have failed. You find yourself in oblivions long hallway with a dead marine at your feet, you grab up the weapons he dropped and charge ahead full.",
	"version": "53c8aa",
	"date": "2013-11-02 15:59:18",
	"files": [
		{
			"filename": "csre2m1.wad",
			"size": 111206,
			"crc": 3282585393,
			"md5": "d35d43c411341cc1a89a22e9096da3dd",
			"sha1": "53c8aaa17680728073d34159d1518d058601f1fb",
			"sha256": "2d725e57ccc1630a5a1aca21179eb3f917f5e627fd45bad166aa43785ae16d28"
		}
	]
}