{
	"uid": "jihaamia (9bae79).wad",
	"name": "For Jihad Ally Mujahid Items ACS Enter Script",
	"description": "You and your cadres set out to embark unto the maps of doom! Adversaries are aware of reinforcements. May God be with you.",
	"version": "9bae79",
	"date": "2017-01-29 00:26:54",
	"files": [
		{
			"filename": "jihaamia.wad",
			"size": 4567613,
			"crc": 2849287427,
			"md5": "08a5fcf62b16d69f4c9a6ed303ba75f4",
			"sha1": "9bae794b483fbd94b1fa9f496c572ecb126338c8",
			"sha256": "18d626a131b393f79a46b95ca64ba4c1dfafa8acea30257594f96d4d62a71b21"
		}
	]
}