{
	"uid": "mustard.wad",
	"name": "Mustard",
	"description": "This Wad is my best ever. It contains 2 (yes count them 2) excellent deathmatch wads. One was created by one of my friends and I a while back and one was created totally by me. This wad contains 8 new sounds, 3 new songs, and 1 new graphic.",
	"date": "2014-12-15 22:47:36",
	"files": [
		{
			"filename": "mustard.wad",
			"size": 484920,
			"crc": 3285035369,
			"md5": "7d8a42d78996f335c129c5064646cb80",
			"sha1": "3f3fceafc5f4b3791c13872b2b0b3bdd0875ac1e",
			"sha256": "191fee89945b180a2ca8c1051f02a11f3ecf3ef7e7bc5b9e5bd6c737145437ed"
		}
	]
}