{
	"uid": "ab-team.wad",
	"name": "THE AB TEAM! V1.0",
	"description": "This is the first cooperative DeathMatch play in the Heretic's history! Grab three dudes and form the cooperative A and B teams... Then, go kill'hem! All weapons are present and an EXIT is also existing. For more exciting, I have added some ;) monsters.",
	"date": "2013-11-02 16:39:27",
	"files": [
		{
			"filename": "ab-team.wad",
			"size": 55488,
			"crc": 3475424773,
			"md5": "8db20b6b37d9c35154264aed655328ac",
			"sha1": "a93b8e79a7421e7bb30841eb7f8f420871b22c72",
			"sha256": "9e3eaa7a8aa95d66a2e439a39624c987195d24690fad51da6dad302f3170aee1"
		}
	]
}