{
	"uid": "OCTOBER (116bb4).wad",
	"name": "October.WAD",
	"description": "Deathmatch Deathmatch Deathmatch This WAD was built with deathamtch in in mind. No safe places to hole up and wait. (I hate it when people do that!) Hunt and kill WAD.",
	"version": "116bb4",
	"date": "2013-11-02 15:19:02",
	"files": [
		{
			"filename": "OCTOBER.wad",
			"size": 54882,
			"crc": 4260995107,
			"md5": "ce34e9e6ba3a7727c32418803262ba47",
			"sha1": "116bb41d0645f1e8d2c447ee114fedc85bb851cd",
			"sha256": "f935e617bc08414e799682ee447d1a89290201359c9e29b5c5b3db46d61f069a"
		}
	]
}