{
	"uid": "SMELODTH.wad",
	"name": "The Smell of Death",
	"description": "Pretty big deathmatch level. This is my first attempt at making a new level, so I made it how I wanted it. (Don't worry. I make a frag-a-second level later.) I would really appreciate feedback on this so I can get better at making .wads.",
	"date": "2014-10-14 21:06:02",
	"files": [
		{
			"filename": "SMELODTH.wad",
			"size": 93557,
			"crc": 2900359819,
			"md5": "a8e69d7d452ce8bead21961cdec428fc",
			"sha1": "9fb72bb8321c8767d2df89f7144e29ed12d8c332",
			"sha256": "af9ab4214b5a7cf3f70c55fd10e9409a91ff92b6e2494d8acebca52b06e022c7"
		}
	]
}