{
	"uid": "uuuhhhtod.wad",
	"name": "uuuhhhtod",
	"description": "This map was made for doom_marine666's unreleased jokewad project called \"Uuuhhh, the stupid mission\". All of the action takes place in a 432x432 space, except three inescapable death pits.",
	"date": "2013-04-19 01:17:57",
	"files": [
		{
			"filename": "uuuhhhtod.wad",
			"size": 186645,
			"crc": 2691857582,
			"md5": "2534f80e8eb7623d9e0f748fa56f041e",
			"sha1": "c7a4bf8cb8baaac467b3ed802efc72bff4a941ef",
			"sha256": "1b16fbd784a71a8aa40dceeca228a9651d6c0077fc6d11cd9365def38b6ab45b"
		}
	]
}