{
	"uid": "zandor2.wad",
	"name": "Zandor2",
	"description": "This wad is one of an undetermined number of levels. After ETERNAL and all of the wonderful new textures, I wanted to build a level using the original DOOM2 textures. Not an easy task with all of the new textures that were at my fingertips. But, I wanted to try, and I had a great time doing it.",
	"date": "2015-01-14 22:55:45",
	"files": [
		{
			"filename": "zandor2.wad",
			"size": 536441,
			"crc": 3615770564,
			"md5": "f42ee1001d3457c450c4b538a91d4b8e",
			"sha1": "fc785734c8e693e44304f1ee2978d190b261719f",
			"sha256": "c208304d6320678e0faa6bd5c4dcda7f81d3d2e2da4576bac3a5f33ac4719907"
		}
	]
}