{
	"uid": "hotsaint.wad",
	"name": "Hall Of The Saint",
	"description": "You came into this place and then there were these monsters and you grabbed some weapons and bombs and you also read some magic books and throwed some eggs and killed the monsters with the stuff and magic and then you found the exit and went on your way.",
	"date": "2014-12-14 23:09:45",
	"files": [
		{
			"filename": "hotsaint.wad",
			"size": 138166,
			"crc": 639191838,
			"md5": "c8b8e8f391d395b831b48f364cb926ca",
			"sha1": "efc7e8686c1d6898e91c54faedcf98f6cd171a52",
			"sha256": "18f731c0293294e5e82077d15db13486d6e377f4a412811afc5dfef955eb64a5"
		}
	]
}