{
	"uid": "ARENA666.wad",
	"name": ":The Deathmatch Arena",
	"description": ":a deathmatch level with 2 large rooms. One has pillars in it, the other a crushing ceiling activated by the switch. this level is very fair. it is not just a fight to see who gets to the good spot first. you'll love this level if you like deathmatch.",
	"date": "2014-08-30 14:28:55",
	"files": [
		{
			"filename": "ARENA666.wad",
			"size": 42698,
			"crc": 1122055567,
			"md5": "d4f1ec6465b62c6a284e0ee93fa22a23",
			"sha1": "1e6b7cffecfbd071801590502ebd64b9861cf95d",
			"sha256": "5ef2ad4d6bb5fb9c7faf0aa0f4010568c7e658adb3ce58e3cef65a5369447fb5"
		}
	]
}