{
	"uid": "the prison.wad",
	"name": "The Prison",
	"description": "This is level number three for me, and i would say its the best ive done so far. The level is'nt quite so linear in its design as my last two efforts, difficulty settings have been applied (unlike my prvious two maps) and this is just generally more of a challenege.",
	"date": "2014-12-29 08:44:39",
	"files": [
		{
			"filename": "the prison.wad",
			"size": 766830,
			"crc": 2250930501,
			"md5": "ab240dcd649e1a4bcc595cd74f80dc9d",
			"sha1": "1e9873d9afc4062da8c2943a43bd94f70ff76c17",
			"sha256": "d6f7cc3ea2ff7b4c6292b1fccb3e218e5ae33b382673e6dea4b43f53689a70a1"
		}
	]
}