{
	"uid": "nib.wad",
	"name": "Nativity in Black",
	"description": "In Italy they have a thing called \"Presepe\" (Crib), a scenographic rappresentation of the Nativity. I tried to do the same using the DooM monsters. This is not blasphemous: the original \"Presepe\" may contain characters like Bin Laden or Bush or (more often) characters famous in Italy.",
	"date": "2015-01-13 21:34:17",
	"files": [
		{
			"filename": "nib.wad",
			"size": 54108,
			"crc": 1992600667,
			"md5": "ae32b51b4e1a364012fa0bf932a7a156",
			"sha1": "58297f8088f33de4d839902b8a77804b7515323c",
			"sha256": "b482fc78246db17bac64352e3994cb73d8a937bcb8a186435454bfe2a3f78d4b"
		}
	]
}